tpds_extension/secureboot/extension.yaml
tpds_extension/secureboot/setup.py
tpds_extension/secureboot/version.py
tpds_extension/secureboot/backend/__init__.py
tpds_extension/secureboot/backend/Tools/FWmetadatatool/FirmwareMetadata.xsd
tpds_extension/secureboot/backend/Tools/FWmetadatatool/SecureFlashPage0.xml
tpds_extension/secureboot/backend/Tools/FWmetadatatool/crypto-46.dll
tpds_extension/secureboot/backend/Tools/FWmetadatatool/hsmSecureFlash.xsd
tpds_extension/secureboot/backend/Tools/FWmetadatatool/hsmsfmdgen.exe
tpds_extension/secureboot/backend/Tools/FWmetadatatool/jsoncpp.dll
tpds_extension/secureboot/backend/Tools/FWmetadatatool/outputfwmd.hex
tpds_extension/secureboot/backend/Tools/FWmetadatatool/outputs.hex
tpds_extension/secureboot/backend/Tools/FWmetadatatool/pic32cksg01FwMd.xml
tpds_extension/secureboot/backend/Tools/FWmetadatatool/pic32czca90FwMd.xml
tpds_extension/secureboot/backend/Tools/FWmetadatatool/pic32czca90FwMdEmpty.xml
tpds_extension/secureboot/backend/Tools/FWmetadatatool/readme.txt
tpds_extension/secureboot/backend/Tools/FWmetadatatool/sbout.txt
tpds_extension/secureboot/backend/Tools/FWmetadatatool/ssl-48.dll
tpds_extension/secureboot/backend/Tools/FWmetadatatool/tls-20.dll
tpds_extension/secureboot/backend/Tools/FWmetadatatool/xerces-c_3_2.dll
tpds_extension/secureboot/backend/boards/pic32cxsg.yaml
tpds_extension/secureboot/backend/boards/EV09H35A/EV09H35A.hex
tpds_extension/secureboot/backend/boards/EV16W43A/EV16W43A.hex
tpds_extension/secureboot/backend/boards/EV33A17A/EV33A17A.hex
tpds_extension/secureboot/backend/boards/PIC32CKSG01/PIC32CKSG01.png
tpds_extension/secureboot/backend/boards/PIC32CKSG01/pic32cksg01_disable_secureboot.hex
tpds_extension/secureboot/backend/boards/PIC32CKSG01/pic32cksg01_hsm.hex
tpds_extension/secureboot/backend/boards/PIC32CKSG01/pic32cksg01_kit_image.hex
tpds_extension/secureboot/backend/boards/PIC32CKSG01/pic32cksg01_led_app_dev.hex
tpds_extension_secureboot-1.3.2.dist-info/METADATA
tpds_extension_secureboot-1.3.2.dist-info/WHEEL
tpds_extension_secureboot-1.3.2.dist-info/top_level.txt
tpds_extension_secureboot-1.3.2.dist-info/RECORD
