Metadata-Version: 2.4
Name: tpds-extension-secureboot
Version: 1.3.2
Summary: Microchip(SPG) Trust Platform - Secureboot extension
Home-page: https://www.microchip.com/TrustPlatform
Author: Microchip Technology
Author-email: SPG.Tools@microchip.com
Classifier: License :: Other/Proprietary License
Classifier: Development Status :: 4 - Beta
Classifier: Programming Language :: Python :: 3
Classifier: Operating System :: OS Independent
Requires-Python: >=3.8
Requires-Dist: tpds-core>2.3.2
Requires-Dist: tpds-helper>2.3.2
